asphodel/unit_formatter.py
asphodel/decoder.py
asphodel/device_info.py
asphodel/enums.py
asphodel/version.py
asphodel/device.py
asphodel/apdparse.py
asphodel/cache.py
asphodel/__init__.py
asphodel/nvmeditor.py
asphodel/streamutil.py
asphodel/clib.py
asphodel/lib/libasphodel.dylib
asphodel-2.0.0.dist-info/RECORD
asphodel-2.0.0.dist-info/WHEEL
asphodel-2.0.0.dist-info/entry_points.txt
asphodel-2.0.0.dist-info/METADATA
asphodel-2.0.0.dist-info/licenses/LICENSE.txt
