Metadata-Version: 2.4
Name: asphodel
Version: 2.0.0
Summary: Python wrapper for the Asphodel library
Keywords: asphodel,suprock
Author-Email: Suprock Technologies <inquiries@suprocktech.com>
License-Expression: ISC
License-File: LICENSE.txt
Classifier: Programming Language :: Python :: 3
Classifier: Operating System :: OS Independent
Classifier: Topic :: System :: Hardware
Project-URL: Repository, https://bitbucket.org/suprocktech/asphodel_py
Requires-Python: >=3.10
Requires-Dist: numpy
